qqq/__init__.py
qqq/github.py
qqq/qqq.py
3q-0.1.6.dist-info/entry_points.txt
3q-0.1.6.dist-info/LICENSE
3q-0.1.6.dist-info/WHEEL
3q-0.1.6.dist-info/METADATA
3q-0.1.6.dist-info/RECORD
