Metadata-Version: 2.1
Name: 3q
Version: 0.1.6
Summary: 
License: MIT
Author: Adam Walsh
Author-email: adamtwalsh@gmail.com
Requires-Python: >=3.6,<4.0
Classifier: License :: OSI Approved :: MIT License
Classifier: Programming Language :: Python :: 3
Classifier: Programming Language :: Python :: 3.6
Classifier: Programming Language :: Python :: 3.7
Classifier: Programming Language :: Python :: 3.8
Requires-Dist: click (>=7.1.2,<8.0.0)
Requires-Dist: click-spinner (>=0.1.10,<0.2.0)
Requires-Dist: gitpython (>=3.1.3,<4.0.0)
Requires-Dist: requests (>=2.24.0,<3.0.0)
Requires-Dist: shortuuid (>=1.0.1,<2.0.0)
